[
    {
        "name": "gameManagerPrimary",
        "type": "address",
        "slot": 0
    },
    {
        "name": "gameManagerSecondary",
        "type": "address",
        "slot": 1
    },
    {
        "name": "bankManager",
        "type": "address",
        "slot": 2
    },
    {
        "name": "paused",
        "type": "bool",
        "slot": 3
    },
    {
        "name": "error",
        "type": "bool",
        "slot": 4
    },
    {
        "name": "allPreSaleItems",
        "type": "CSCPreSaleItem[]",
        "slot": 5
    },
    {
        "name": "prometheusShipMinted",
        "type": "uint256",
        "slot": 6
    },
    {
        "name": "intrepidShipMinted",
        "type": "uint256",
        "slot": 7
    },
    {
        "name": "crosairShipMinted",
        "type": "uint256",
        "slot": 8
    },
    {
        "name": "prometheusVouchersMinted",
        "type": "uint256",
        "slot": 9
    },
    {
        "name": "intrepidVouchersMinted",
        "type": "uint256",
        "slot": 10
    },
    {
        "name": "crosairVouchersMinted",
        "type": "uint256",
        "slot": 11
    },
    {
        "name": "approvedAddressList",
        "type": "mapping(address => bool)",
        "slot": 12
    },
    {
        "name": "preSaleItemIndexToOwner",
        "type": "mapping(uint256 => address)",
        "slot": 13
    },
    {
        "name": "ownershipTokenCount",
        "type": "mapping(address => uint256)",
        "slot": 14
    },
    {
        "name": "preSaleItemIndexToApproved",
        "type": "mapping(uint256 => address)",
        "slot": 15
    },
    {
        "name": "preSaleItemTypeToSequenceIdToCollectible",
        "type": "mapping(uint256 => mapping(uint256 => mapping(uint256 => uint256)))",
        "slot": 16
    },
    {
        "name": "preSaleItemTypeToCollectibleCount",
        "type": "mapping(uint256 => mapping(uint256 => uint256))",
        "slot": 17
    },
    {
        "name": "PROMETHEUS_SHIP_PRICE",
        "type": "uint256",
        "slot": 18
    },
    {
        "name": "INTREPID_SHIP_PRICE",
        "type": "uint256",
        "slot": 19
    },
    {
        "name": "CROSAIR_SHIP_PRICE",
        "type": "uint256",
        "slot": 20
    },
    {
        "name": "prometheusSoldCount",
        "type": "uint256",
        "slot": 21
    },
    {
        "name": "intrepidSoldCount",
        "type": "uint256",
        "slot": 22
    },
    {
        "name": "crosairSoldCount",
        "type": "uint256",
        "slot": 23
    },
    {
        "name": "PROMETHEUS_VOUCHER_PRICE",
        "type": "uint256",
        "slot": 24
    },
    {
        "name": "INTREPID_VOUCHER_PRICE",
        "type": "uint256",
        "slot": 25
    },
    {
        "name": "CROSAIR_VOUCHER_PRICE",
        "type": "uint256",
        "slot": 26
    },
    {
        "name": "prometheusVoucherSoldCount",
        "type": "uint256",
        "slot": 27
    },
    {
        "name": "crosairVoucherSoldCount",
        "type": "uint256",
        "slot": 28
    },
    {
        "name": "intrepidVoucherSoldCount",
        "type": "uint256",
        "slot": 29
    },
    {
        "name": "addressToValue",
        "type": "mapping(address => uint256)",
        "slot": 30
    },
    {
        "name": "addressToCollectibleTypeBalance",
        "type": "mapping(address => mapping(uint256 => mapping(uint256 => uint256)))",
        "slot": 31
    },
    {
        "name": "CSCPreSaleInit",
        "type": "bool",
        "slot": 32
    }
]